fastapi_chameleon/__init__.py
fastapi_chameleon/engine.py
fastapi_chameleon/exceptions.py
fastapi_chameleon-0.1.17.dist-info/METADATA
fastapi_chameleon-0.1.17.dist-info/WHEEL
fastapi_chameleon-0.1.17.dist-info/licenses/LICENSE
fastapi_chameleon-0.1.17.dist-info/RECORD
