Metadata-Version: 2.4
Name: fastapi_chameleon
Version: 0.1.17
Summary: Adds integration of the Chameleon template language to FastAPI.
Project-URL: Homepage, https://github.com/mikeckennedy/fastapi-chameleon
Author-email: Michael Kennedy <michael@talkpython.fm>
License: MIT
License-File: LICENSE
Keywords: Chameleon,FastAPI,integration,template
Classifier: Development Status :: 5 - Production/Stable
Classifier: License :: OSI Approved :: MIT License
Classifier: Programming Language :: Python
Classifier: Programming Language :: Python :: 3.10
Classifier: Programming Language :: Python :: 3.11
Classifier: Programming Language :: Python :: 3.12
Classifier: Programming Language :: Python :: 3.13
Classifier: Programming Language :: Python :: 3.14
Requires-Python: >=3.10
Requires-Dist: chameleon
Requires-Dist: fastapi
